orm/khmeri/__init__.py
orm/khmeri/database.py
orm/khmeri/logger.py
orm/khmeri/manager.py
orm/khmeri/model.py
khmeri-0.0.1.dist-info/LICENSE
khmeri-0.0.1.dist-info/METADATA
khmeri-0.0.1.dist-info/WHEEL
khmeri-0.0.1.dist-info/top_level.txt
khmeri-0.0.1.dist-info/RECORD
