Metadata-Version: 2.1
Name: khmeri
Version: 0.0.1
Summary: A small example package
Author-email: bazgab <gabrielbzzt@gmail.com>
Project-URL: Homepage, https://github.com/bazgab/khmeri
Project-URL: Issues, https://github.com/bazgab/khmeri/issues
Classifier: Programming Language :: Python :: 3
Classifier: License :: OSI Approved :: MIT License
Classifier: Operating System :: Unix
Requires-Python: >=3.8
License-File: LICENSE
